listcondalic/__init__.py
listcondalic/_version.py
listcondalic/conda_search_based.py
listcondalic/liccheck_and_condameta_based.py
listcondalic/modified_liccheck.py
listcondalic/utils.py
listcondalic-0.1.1.dist-info/LICENSE
listcondalic-0.1.1.dist-info/METADATA
listcondalic-0.1.1.dist-info/WHEEL
listcondalic-0.1.1.dist-info/entry_points.txt
listcondalic-0.1.1.dist-info/top_level.txt
listcondalic-0.1.1.dist-info/RECORD
