Metadata-Version: 2.1
Name: listcondalic
Version: 0.1.1
Summary: List license requirement of a project based on configuration file.
Home-page: https://github.com/we-taper/listcondalic
Author: Taper
Author-email: hongxiang.chen.94@gmail.com
License: UNKNOWN
Project-URL: Bug Reports, https://github.com/we-taper/listcondalic/issues
Project-URL: Source, https://github.com/we-taper/listcondalic/
Keywords: license,compliance,development
Platform: UNKNOWN
Classifier: Development Status :: 3 - Alpha
Classifier: Intended Audience :: Developers
Classifier: Topic :: Software Development :: Build Tools
Classifier: License :: OSI Approved :: GNU General Public License v3 (GPLv3)
Classifier: Programming Language :: Python :: 3
Classifier: Programming Language :: Python :: 3.7
Classifier: Programming Language :: Python :: 3.8
Classifier: Programming Language :: Python :: 3.9
Classifier: Programming Language :: Python :: 3 :: Only
Requires-Python: >=3.7, <4
Requires-Dist: click
Requires-Dist: liccheck (==0.6.2)
Requires-Dist: loguru (==0.5.3)
Requires-Dist: pip-licenses (==3.5.1)
Requires-Dist: pydantic
Requires-Dist: pyyaml
